icl_evaluator/__init__.py
icl_evaluator/icl_acc_evaluator.py
icl_evaluator/icl_api_evaluator.py
icl_evaluator/icl_base_evaluator.py
icl_evaluator/icl_bleu_evaluator.py
icl_evaluator/icl_rouge_evaluator.py
icl_evaluator/icl_squad_evaluator.py
icl_inferencer/__init__.py
icl_inferencer/icl_base_inferencer.py
icl_inferencer/icl_channel_inferencer.py
icl_inferencer/icl_cot_inferencer.py
icl_inferencer/icl_gen_inferencer.py
icl_inferencer/icl_ppl_inferencer.py
icl_retriever/__init__.py
icl_retriever/icl_base_retriever.py
icl_retriever/icl_bm25_retriever.py
icl_retriever/icl_dpp_retriever.py
icl_retriever/icl_mdl_retriever.py
icl_retriever/icl_random_retriever.py
icl_retriever/icl_topk_retriever.py
icl_retriever/icl_votek_retriever.py
icl_retriever/icl_zero_retriever.py
utils/__init__.py
utils/api_service.py
utils/calculate.py
utils/check_type.py
utils/collators.py
utils/icl_common_utils.py
utils/logging.py
openicl_unlabel-0.0.1.dist-info/METADATA
openicl_unlabel-0.0.1.dist-info/WHEEL
openicl_unlabel-0.0.1.dist-info/top_level.txt
openicl_unlabel-0.0.1.dist-info/RECORD
